AUTHORS
CHANGELOG.txt
DESCRIPTION
LICENSE
MANIFEST.in
README.rst
requirements.txt
setup.py
django_openinghours.egg-info/PKG-INFO
django_openinghours.egg-info/SOURCES.txt
django_openinghours.egg-info/dependency_links.txt
django_openinghours.egg-info/requires.txt
django_openinghours.egg-info/top_level.txt
docs/UPGRADING.rst
openinghours/__init__.py
openinghours/admin.py
openinghours/app_settings.py
openinghours/forms.py
openinghours/models.py
openinghours/urls.py
openinghours/utils.py
openinghours/views.py
openinghours/views_edit.py
openinghours/migrations/0001_initial.py
openinghours/migrations/0002_auto_20170915_0912.py
openinghours/migrations/__init__.py
openinghours/static/.empty
openinghours/static/openinghours/.empty
openinghours/templates/openinghours/base.html
openinghours/templates/openinghours/edit_base.html
openinghours/templates/openinghours/edit_form.html
openinghours/templates/openinghours/index.html
openinghours/templates/openinghours/opening_hours_list.html
openinghours/templates/openinghours/opening_hours_list_concise.html
openinghours/templatetags/__init__.py
openinghours/templatetags/openinghours_tags.py
openinghours/tests/__init__.py
openinghours/tests/test_forms.py
openinghours/tests/test_settings.py
openinghours/tests/test_templatetags.py
openinghours/tests/tests.py