Metadata-Version: 1.0
Name: django-openinghours
Version: 0.1.5
Summary: A reusable Django app to work with opening hours.
